inletscolab/__init__.py
inletscolab/client.py
inletscolab/cmd.py
inletscolab/config.py
inletscolab/inlets.py
inletscolab/server.py
inletscolab-0.0.1.dist-info/METADATA
inletscolab-0.0.1.dist-info/WHEEL
inletscolab-0.0.1.dist-info/entry_points.txt
inletscolab-0.0.1.dist-info/top_level.txt
inletscolab-0.0.1.dist-info/RECORD
