Metadata-Version: 2.1
Name: inletscolab
Version: 0.0.1
Summary: Port Forward using Inlets with Colab
Home-page: https://github.com/trisongz/inlets-colab
Author: trisongz
Author-email: ts@growthengineai.com
License: MIT Style
Platform: UNKNOWN
Classifier: Intended Audience :: Developers
Classifier: License :: OSI Approved :: MIT License
Classifier: Programming Language :: Python :: 3.7
Classifier: Topic :: Software Development :: Libraries
Requires-Python: >=3.7
Requires-Dist: lazycls
Requires-Dist: pylogz
Requires-Dist: typer
